agentos_taskweaver-0.1.0.dist-info/licenses/LICENSE
taskweaver/__init__.py
taskweaver/__main__.py
taskweaver/app/__init__.py
taskweaver/app/app.py
taskweaver/app/session_manager.py
taskweaver/app/session_store.py
taskweaver/ces/__init__.py
taskweaver/ces/client.py
taskweaver/ces/common.py
taskweaver/ces/environment.py
taskweaver/ces/kernel/__init__.py
taskweaver/ces/kernel/config.py
taskweaver/ces/kernel/ctx_magic.py
taskweaver/ces/kernel/ext.py
taskweaver/ces/kernel/kernel_logging.py
taskweaver/ces/kernel/launcher.py
taskweaver/ces/manager/__init__.py
taskweaver/ces/manager/defer.py
taskweaver/ces/manager/sub_proc.py
taskweaver/ces/runtime/__init__.py
taskweaver/ces/runtime/context.py
taskweaver/ces/runtime/executor.py
taskweaver/chat/__init__.py
taskweaver/chat/console/__init__.py
taskweaver/chat/console/__main__.py
taskweaver/chat/console/chat.py
taskweaver/cli/__init__.py
taskweaver/cli/__main__.py
taskweaver/cli/chat.py
taskweaver/cli/cli.py
taskweaver/cli/init.py
taskweaver/cli/taskweaver-project.zip
taskweaver/cli/util.py
taskweaver/cli/web.py
taskweaver/code_interpreter/__init__.py
taskweaver/code_interpreter/code_executor.py
taskweaver/code_interpreter/code_verification.py
taskweaver/code_interpreter/interpreter.py
taskweaver/code_interpreter/plugin_selection.py
taskweaver/code_interpreter/code_interpreter/__init__.py
taskweaver/code_interpreter/code_interpreter/code_generator.py
taskweaver/code_interpreter/code_interpreter/code_generator_prompt.yaml
taskweaver/code_interpreter/code_interpreter/code_interpreter.py
taskweaver/code_interpreter/code_interpreter/code_interpreter.role.yaml
taskweaver/code_interpreter/code_interpreter/compression_prompt.yaml
taskweaver/code_interpreter/code_interpreter_cli_only/__init__.py
taskweaver/code_interpreter/code_interpreter_cli_only/code_generator_cli_only.py
taskweaver/code_interpreter/code_interpreter_cli_only/code_generator_prompt_cli_only.yaml
taskweaver/code_interpreter/code_interpreter_cli_only/code_interpreter_cli_only.py
agentos_taskweaver-0.1.0.dist-info/METADATA
agentos_taskweaver-0.1.0.dist-info/WHEEL
agentos_taskweaver-0.1.0.dist-info/entry_points.txt
agentos_taskweaver-0.1.0.dist-info/top_level.txt
agentos_taskweaver-0.1.0.dist-info/RECORD
