Metadata-Version: 2.4
Name: agentos-taskweaver
Version: 0.1.0
Summary: A code-first agent framework for seamlessly planning and executing data analytics tasks
Author: Microsoft Taskweaver
Author-email: Microsoft TaskWeaver Team <taskweaver@microsoft.com>
Maintainer-email: Microsoft TaskWeaver Team <taskweaver@microsoft.com>
License:     MIT License
Project-URL: Homepage, https://github.com/microsoft/TaskWeaver
Project-URL: Documentation, https://microsoft.github.io/TaskWeaver/
Project-URL: Repository, https://github.com/microsoft/TaskWeaver
Project-URL: Bug Tracker, https://github.com/microsoft/TaskWeaver/issues
Project-URL: Changelog, https://github.com/microsoft/TaskWeaver/blob/main/CHANGELOG.md
Keywords: ai,agent,llm,data-analytics,code-generation,planning
Classifier: Development Status :: 4 - Beta
Classifier: Intended Audience :: Developers
Classifier: Intended Audience :: Science/Research
Classifier: License :: OSI Approved :: MIT License
Classifier: Operating System :: OS Independent
Classifier: Programming Language :: Python :: 3
Classifier: Programming Language :: Python :: 3.10
Classifier: Programming Language :: Python :: 3.11
Classifier: Programming Language :: Python :: 3.12
Classifier: Topic :: Scientific/Engineering :: Artificial Intelligence
Classifier: Topic :: Software Development :: Libraries :: Python Modules
Requires-Python: >=3.10
License-File: LICENSE
Requires-Dist: numpy>=1.24.2
Requires-Dist: pandas>=2.0.0
Requires-Dist: matplotlib>=3.4
Requires-Dist: seaborn>=0.11
Requires-Dist: python-dotenv>=1.0.0
Requires-Dist: openai>=1.42.0
Requires-Dist: pydantic>=2.8.2
Requires-Dist: pyyaml>=6.0
Requires-Dist: scikit-learn>=1.2.2
Requires-Dist: click>=8.0.1
Requires-Dist: urllib3>=1.26.17
Requires-Dist: jsonschema>=4.20.0
Requires-Dist: injector>=0.21.0
Requires-Dist: ijson>=3.2.3
Requires-Dist: requests>=2.31.0
Requires-Dist: docker>=7.0.0
Requires-Dist: ipykernel==6.26.0
Requires-Dist: tenacity>=8.2.2
Requires-Dist: plotly>=5.14.1
Requires-Dist: colorama>=0.4.6
Provides-Extra: dev
Requires-Dist: pre-commit>=2.19.0; extra == "dev"
Requires-Dist: pytest>=7.0.0; extra == "dev"
Requires-Dist: vcrpy>=5.0.0; extra == "dev"
Requires-Dist: black>=22.0.0; extra == "dev"
Requires-Dist: isort>=5.10.0; extra == "dev"
Requires-Dist: flake8>=4.0.0; extra == "dev"
Provides-Extra: test
Requires-Dist: pytest>=7.0.0; extra == "test"
Requires-Dist: vcrpy>=5.0.0; extra == "test"
Dynamic: author
Dynamic: license-file
Dynamic: requires-python
